humanbytes/__init__.py
humanbytes/humanbytes.py
humanbytes-1.0.0.dist-info/licenses/LICENSE
humanbytes-1.0.0.dist-info/METADATA
humanbytes-1.0.0.dist-info/WHEEL
humanbytes-1.0.0.dist-info/top_level.txt
humanbytes-1.0.0.dist-info/RECORD
