Metadata-Version: 2.4
Name: humanbytes
Version: 1.0.0
Summary: Convert bytes to human-readable sizes (KB, MB, KiB, MiB, etc.)
Home-page: https://github.com/Zsombroo/humanbytes
Author: Zsombroo
License: MIT
Classifier: Programming Language :: Python :: 3
Classifier: Operating System :: OS Independent
Classifier: Intended Audience :: Developers
Classifier: Topic :: Software Development :: Libraries :: Python Modules
Requires-Python: >=3.6
License-File: LICENSE
Dynamic: author
Dynamic: classifier
Dynamic: description
Dynamic: description-content-type
Dynamic: home-page
Dynamic: license
Dynamic: license-file
Dynamic: requires-python
Dynamic: summary
